minibelt.py
minibelt-0.2.2.dist-info/DESCRIPTION.rst
minibelt-0.2.2.dist-info/METADATA
minibelt-0.2.2.dist-info/RECORD
minibelt-0.2.2.dist-info/WHEEL
minibelt-0.2.2.dist-info/metadata.json
minibelt-0.2.2.dist-info/top_level.txt
