Metadata-Version: 2.0
Name: minibelt
Version: 0.2.2
Summary: One-file utility module filled with helper functions for day to day Python programming
Home-page: https://github.com/sametmax/minibelt
Author: Sam et Max
Author-email: lesametlemax@gmail.com
License: UNKNOWN
Platform: UNKNOWN
Classifier: Programming Language :: Python
Classifier: Intended Audience :: Information Technology
Classifier: License :: OSI Approved :: zlib/libpng License
Classifier: Natural Language :: English
Classifier: Programming Language :: Python :: 3.6
